MANIFEST.in
README
requirements.txt
setup.py
ajenti.plugin.settings.egg-info/PKG-INFO
ajenti.plugin.settings.egg-info/SOURCES.txt
ajenti.plugin.settings.egg-info/dependency_links.txt
ajenti.plugin.settings.egg-info/requires.txt
ajenti.plugin.settings.egg-info/top_level.txt
ajenti_plugin_settings/README.md
ajenti_plugin_settings/__init__.py
ajenti_plugin_settings/bower.json
ajenti_plugin_settings/main.py
ajenti_plugin_settings/plugin.yml
ajenti_plugin_settings/requirements.txt
ajenti_plugin_settings/views.py
ajenti_plugin_settings/locale/app.pot
ajenti_plugin_settings/locale/af/LC_MESSAGES/app.js
ajenti_plugin_settings/locale/af/LC_MESSAGES/app.po
ajenti_plugin_settings/locale/af/LC_MESSAGES/app.po~
ajenti_plugin_settings/locale/ar/LC_MESSAGES/app.js
ajenti_plugin_settings/locale/ar/LC_MESSAGES/app.po
ajenti_plugin_settings/locale/ar/LC_MESSAGES/app.po~
ajenti_plugin_settings/locale/be/LC_MESSAGES/app.js
ajenti_plugin_settings/locale/be/LC_MESSAGES/app.po
ajenti_plugin_settings/locale/be/LC_MESSAGES/app.po~
ajenti_plugin_settings/locale/bg/LC_MESSAGES/app.js
ajenti_plugin_settings/locale/bg/LC_MESSAGES/app.po
ajenti_plugin_settings/locale/bg/LC_MESSAGES/app.po~
ajenti_plugin_settings/locale/bn/LC_MESSAGES/app.js
ajenti_plugin_settings/locale/bn/LC_MESSAGES/app.po
ajenti_plugin_settings/locale/bn/LC_MESSAGES/app.po~
ajenti_plugin_settings/locale/bs/LC_MESSAGES/app.js
ajenti_plugin_settings/locale/bs/LC_MESSAGES/app.po
ajenti_plugin_settings/locale/ca/LC_MESSAGES/app.js
ajenti_plugin_settings/locale/ca/LC_MESSAGES/app.po
ajenti_plugin_settings/locale/ca/LC_MESSAGES/app.po~
ajenti_plugin_settings/locale/cs/LC_MESSAGES/app.js
ajenti_plugin_settings/locale/cs/LC_MESSAGES/app.po
ajenti_plugin_settings/locale/cs/LC_MESSAGES/app.po~
ajenti_plugin_settings/locale/da/LC_MESSAGES/app.js
ajenti_plugin_settings/locale/da/LC_MESSAGES/app.po
ajenti_plugin_settings/locale/da/LC_MESSAGES/app.po~
ajenti_plugin_settings/locale/de/LC_MESSAGES/app.js
ajenti_plugin_settings/locale/de/LC_MESSAGES/app.po
ajenti_plugin_settings/locale/de/LC_MESSAGES/app.po~
ajenti_plugin_settings/locale/el/LC_MESSAGES/app.js
ajenti_plugin_settings/locale/el/LC_MESSAGES/app.po
ajenti_plugin_settings/locale/el/LC_MESSAGES/app.po~
